{"cameraMode":{"drawMode":0,"name":"Shaded","section":"Shading Mode"},"sceneLighting":true,"audioPlay":false,"sceneViewState":{"m_AlwaysRefresh":false,"showFog":true,"showSkybox":true,"showFlares":true,"showImageEffects":true,"showParticleSystems":true,"showVisualEffectGraphs":true,"m_FxEnabled":true},"in2DMode":false,"pivot":{"x":-0.22846846282482148,"y":-3.251744508743286,"z":2.989570140838623},"rotation":{"x":0.07224629074335098,"y":0.005979190580546856,"z":-0.00043054387788288295,"w":0.9973909258842468},"size":0.07693840563297272,"orthographic":false}